LICENSE
MANIFEST.in
README.md
requirements.txt
setup.py
carto_etl.egg-info/PKG-INFO
carto_etl.egg-info/SOURCES.txt
carto_etl.egg-info/dependency_links.txt
carto_etl.egg-info/requires.txt
carto_etl.egg-info/top_level.txt
etl/__init__.py
etl/etl.py
etl/geocoding.py