Metadata-Version: 1.0
Name: carto-etl
Version: 1.0.1
Summary: ETL and geocoding functions
Home-page: https://github.com/CartoDB/carto-etl
Author: Daniel Carrión, Alberto Romeu
Author-email: daniel@cartodb.com, alrocar@cartodb.com
License: UNKNOWN
Platform: UNKNOWN
